as_envhelper/__init__.py
as_envhelper/core.py
as_envhelper-1.0.3.dist-info/licenses/LICENSE
test/test_as_envhelper.py
as_envhelper-1.0.3.dist-info/METADATA
as_envhelper-1.0.3.dist-info/WHEEL
as_envhelper-1.0.3.dist-info/top_level.txt
as_envhelper-1.0.3.dist-info/RECORD
