Metadata-Version: 2.4
Name: as-envhelper
Version: 1.0.3
Summary: Simple, beginner-friendly Python environment variable loader with Flask & Django support
Home-page: https://github.com/Aswin-Kumar24072003/as_envhelper
Author: ASWIN KUMAR K
Author-email: ASWIN KUMAR K <aswinkumar06k@gmail.com>
License: GPLv3
Project-URL: homepage, https://github.com/Aswin-Kumar24072003/as_envhelper
Project-URL: bug tracker, https://github.com/Aswin-Kumar24072003/as_envhelper/issues
Keywords: environment variables,dotenv,flask,django,python,loader
Classifier: Development Status :: 5 - Production/Stable
Classifier: Intended Audience :: Developers
Classifier: Programming Language :: Python :: 3
Classifier: License :: OSI Approved :: GNU General Public License v3 (GPLv3)
Classifier: Operating System :: OS Independent
Classifier: Topic :: Software Development :: Libraries :: Python Modules
Requires-Python: >=3.7
License-File: LICENSE
Dynamic: license-file
